rubberduckie/__init__.py
rubberduckie/cdsw/__init__.py
rubberduckie/cdsw/hadoop.py
rubberduckie/cdsw/import_fix.py
rubberduckie/cdsw/misc.py
rubberduckie/da/__init__.py
rubberduckie/da/pilot.py
rubberduckie/dl/__init__.py
rubberduckie/ml/__init__.py
rubberduckie/monitor/runtime.py
rubberduckie/plot/__init__.py
rubberduckie/plot/evaluation.py
rubberduckie/plot/shap_visual.py
rubberduckie/xai/__init__.py
rubberduckie-2025.2.2.dist-info/LICENSE.txt
rubberduckie-2025.2.2.dist-info/METADATA
rubberduckie-2025.2.2.dist-info/WHEEL
rubberduckie-2025.2.2.dist-info/top_level.txt
rubberduckie-2025.2.2.dist-info/RECORD
