Metadata-Version: 2.2
Name: rubberduckie
Version: 2025.2.2
Summary: By Data Scientists and For Data Scientists
Author-email: Colin & Team <colin.syd.au@gmail.com>
Classifier: Programming Language :: Python :: 3
Requires-Python: >=3.7
License-File: LICENSE.txt
Requires-Dist: scikit-learn
Requires-Dist: numpy>=1.21.6
Requires-Dist: matplotlib
Requires-Dist: seaborn
Requires-Dist: pandas
Requires-Dist: tqdm
Provides-Extra: doc
Requires-Dist: sphinx~=7.1.2; extra == "doc"
Requires-Dist: myst-parser~=2.0.0; extra == "doc"
Requires-Dist: furo; extra == "doc"
Requires-Dist: nbsphinx; extra == "doc"
Requires-Dist: sphinx_rtd_theme; extra == "doc"
